fastqcparser/__init__.py
fastqcparser/fastqcparser.py
fastqcparser/release.py
fastqcparser-1.1.dist-info/DESCRIPTION.rst
fastqcparser-1.1.dist-info/METADATA
fastqcparser-1.1.dist-info/RECORD
fastqcparser-1.1.dist-info/WHEEL
fastqcparser-1.1.dist-info/metadata.json
fastqcparser-1.1.dist-info/top_level.txt
tests/__init__.py
tests/test_fastqcparser.py
