Metadata-Version: 2.0
Name: fastqcparser
Version: 1.1
Summary: python API for parsing FastQC output
Home-page: http://bitbucket.org/bubioinformaticshub/fastqcparser
Author: Adam Labadorf
Author-email: labadorf@bu.edu
Maintainer: Adam Labadorf
Maintainer-email: labadorf@bu.edu
License: UNKNOWN
Keywords: bioinformatics fastqc parsing
Platform: UNKNOWN
Classifier: Development Status :: 5 - Production/Stable
Classifier: Operating System :: MacOS :: MacOS X
Classifier: Operating System :: Microsoft :: Windows
Classifier: Operating System :: OS Independent
Classifier: Operating System :: POSIX
Classifier: Programming Language :: Python
Classifier: Programming Language :: Python :: 2.7
Classifier: Programming Language :: Python :: 3
Classifier: Programming Language :: Python :: 3.3
Classifier: Programming Language :: Python :: 3.4
Classifier: Intended Audience :: Developers
Classifier: Intended Audience :: Science/Research
Classifier: Topic :: Scientific/Engineering :: Bio-Informatics
Classifier: Topic :: Software Development :: Libraries :: Python Modules
Classifier: Topic :: Utilities
